magma_rsam/__init__.py
magma_rsam/plot_rsam.py
magma_rsam/rsam.py
magma_rsam/rsam_trace.py
magma_rsam/validator.py
magma_rsam-1.8.2.dist-info/licenses/LICENSE
magma_rsam-1.8.2.dist-info/WHEEL
magma_rsam-1.8.2.dist-info/METADATA
magma_rsam-1.8.2.dist-info/RECORD
