Metadata-Version: 2.4
Name: magma-rsam
Version: 1.8.2
Summary: Calculating RSAM Value
Keywords: seismic,volcano,volcanology,convert,sds,seiscomp,mseed
Author-email: Martanto <martanto@live.com>, Devy Kamil Syahbana <devy.syahbana@gmail.com>, Syarif Abdul Manaf <riefmof@gmail.com>
Requires-Python: >=3.11
Classifier: License :: OSI Approved :: MIT License
Classifier: Operating System :: OS Independent
Classifier: Programming Language :: Python :: 3.11
Classifier: Programming Language :: Python :: 3.12
License-File: LICENSE
Requires-Dist: obspy>=1.4.2
Requires-Dist: openpyxl>=3.1.5
Requires-Dist: pandas>=2.2.2
Requires-Dist: numpy>=2.2.5
Requires-Dist: matplotlib>=3.9.0
Requires-Dist: magma-database>=1.5.0
Requires-Dist: magma-converter>=1.9.0
Requires-Dist: questdb[dataframe]>=2.0.3
Requires-Dist: peewee>=3.17.5
Requires-Dist: material-color
Requires-Dist: tqdm
Requires-Dist: obspy ; extra == "base"
Requires-Dist: openpyxl ; extra == "base"
Requires-Dist: pandas ; extra == "base"
Requires-Dist: numpy ; extra == "base"
Requires-Dist: matplotlib ; extra == "base"
Requires-Dist: magma-database ; extra == "base"
Requires-Dist: questdb[dataframe] ; extra == "base"
Requires-Dist: peewee ; extra == "base"
Requires-Dist: magma-converter ; extra == "base"
Requires-Dist: material-color ; extra == "base"
Project-URL: Homepage, https://github.com/martanto/magma-rsam
Project-URL: Issues, https://github.com/martanto/magma-rsam/issues
Provides-Extra: base
